photovoltaic/ASTMG173.txt
photovoltaic/__init__.py
photovoltaic/cell.py
photovoltaic/cell_info.txt
photovoltaic/core.py
photovoltaic/money.py
photovoltaic/optic.py
photovoltaic/panel.py
photovoltaic/semi.py
photovoltaic/si.py
photovoltaic/silicon_optical_properties.txt
photovoltaic/sort_def.py
photovoltaic/sorted.py
photovoltaic/sun.py
photovoltaic/sun_sort.py
photovoltaic-0.1.9.dist-info/LICENCE.txt
photovoltaic-0.1.9.dist-info/METADATA
photovoltaic-0.1.9.dist-info/WHEEL
photovoltaic-0.1.9.dist-info/top_level.txt
photovoltaic-0.1.9.dist-info/RECORD
